<?xml version="1.0" encoding="utf-8"?>
<Resources Culture="en-US">
	<Group Type="String">
		<Items>
			<Item Name="BaseElements.ChangeDataUserTask3.Caption" Value="Modify Request-TransferIn" />
			<Item Name="BaseElements.ChangeDataUserTask3.Parameters.ConsiderTimeInFilter.Caption" Value="Consider time in the filter" />
			<Item Name="BaseElements.ChangeDataUserTask3.Parameters.ConsiderTimeInFilter.DisplayValue" Value="true" />
			<Item Name="BaseElements.ChangeDataUserTask3.Parameters.DataSourceFilters.Caption" Value="Data source filters" />
			<Item Name="BaseElements.ChangeDataUserTask3.Parameters.EntitySchemaUId.Caption" Value="Object" />
			<Item Name="BaseElements.ChangeDataUserTask3.Parameters.IsMatchConditions.Caption" Value="If object meets the following conditions" />
			<Item Name="BaseElements.ChangeDataUserTask3.Parameters.IsMatchConditions.DisplayValue" Value="true" />
			<Item Name="BaseElements.ChangeDataUserTask3.Parameters.RecordColumnValues.Caption" Value="Set column values" />
			<Item Name="BaseElements.ChangeDataUserTask4.Caption" Value="Modify Request-TransferIn - SR" />
			<Item Name="BaseElements.ChangeDataUserTask4.Parameters.ConsiderTimeInFilter.Caption" Value="Consider time in the filter" />
			<Item Name="BaseElements.ChangeDataUserTask4.Parameters.ConsiderTimeInFilter.DisplayValue" Value="true" />
			<Item Name="BaseElements.ChangeDataUserTask4.Parameters.DataSourceFilters.Caption" Value="Data source filters" />
			<Item Name="BaseElements.ChangeDataUserTask4.Parameters.EntitySchemaUId.Caption" Value="Object" />
			<Item Name="BaseElements.ChangeDataUserTask4.Parameters.IsMatchConditions.Caption" Value="If object meets the following conditions" />
			<Item Name="BaseElements.ChangeDataUserTask4.Parameters.IsMatchConditions.DisplayValue" Value="true" />
			<Item Name="BaseElements.ChangeDataUserTask4.Parameters.RecordColumnValues.Caption" Value="Set column values" />
			<Item Name="BaseElements.ChangeDataUserTask5.Caption" Value="Modify Request-TransferOut - SR" />
			<Item Name="BaseElements.ChangeDataUserTask5.Parameters.ConsiderTimeInFilter.Caption" Value="Consider time in the filter" />
			<Item Name="BaseElements.ChangeDataUserTask5.Parameters.ConsiderTimeInFilter.DisplayValue" Value="true" />
			<Item Name="BaseElements.ChangeDataUserTask5.Parameters.DataSourceFilters.Caption" Value="Data source filters" />
			<Item Name="BaseElements.ChangeDataUserTask5.Parameters.EntitySchemaUId.Caption" Value="Object" />
			<Item Name="BaseElements.ChangeDataUserTask5.Parameters.IsMatchConditions.Caption" Value="If object meets the following conditions" />
			<Item Name="BaseElements.ChangeDataUserTask5.Parameters.IsMatchConditions.DisplayValue" Value="true" />
			<Item Name="BaseElements.ChangeDataUserTask5.Parameters.RecordColumnValues.Caption" Value="Set column values" />
			<Item Name="BaseElements.ChangeDataUserTask6.Caption" Value="Modify Request-TransferIn - mfund" />
			<Item Name="BaseElements.ChangeDataUserTask6.Parameters.ConsiderTimeInFilter.Caption" Value="Consider time in the filter" />
			<Item Name="BaseElements.ChangeDataUserTask6.Parameters.ConsiderTimeInFilter.DisplayValue" Value="true" />
			<Item Name="BaseElements.ChangeDataUserTask6.Parameters.DataSourceFilters.Caption" Value="Data source filters" />
			<Item Name="BaseElements.ChangeDataUserTask6.Parameters.EntitySchemaUId.Caption" Value="Object" />
			<Item Name="BaseElements.ChangeDataUserTask6.Parameters.IsMatchConditions.Caption" Value="If object meets the following conditions" />
			<Item Name="BaseElements.ChangeDataUserTask6.Parameters.IsMatchConditions.DisplayValue" Value="true" />
			<Item Name="BaseElements.ChangeDataUserTask6.Parameters.RecordColumnValues.Caption" Value="Set column values" />
			<Item Name="BaseElements.ChangeDataUserTask7.Caption" Value="Modify Request-TransferOut - mfund" />
			<Item Name="BaseElements.ChangeDataUserTask7.Parameters.ConsiderTimeInFilter.Caption" Value="Consider time in the filter" />
			<Item Name="BaseElements.ChangeDataUserTask7.Parameters.ConsiderTimeInFilter.DisplayValue" Value="true" />
			<Item Name="BaseElements.ChangeDataUserTask7.Parameters.DataSourceFilters.Caption" Value="Data source filters" />
			<Item Name="BaseElements.ChangeDataUserTask7.Parameters.EntitySchemaUId.Caption" Value="Object" />
			<Item Name="BaseElements.ChangeDataUserTask7.Parameters.IsMatchConditions.Caption" Value="If object meets the following conditions" />
			<Item Name="BaseElements.ChangeDataUserTask7.Parameters.IsMatchConditions.DisplayValue" Value="true" />
			<Item Name="BaseElements.ChangeDataUserTask7.Parameters.RecordColumnValues.Caption" Value="Set column values" />
			<Item Name="BaseElements.ChangeDataUserTask9.Caption" Value="Modify Request-TransferOut" />
			<Item Name="BaseElements.ChangeDataUserTask9.Parameters.ConsiderTimeInFilter.Caption" Value="Consider time in the filter" />
			<Item Name="BaseElements.ChangeDataUserTask9.Parameters.ConsiderTimeInFilter.DisplayValue" Value="true" />
			<Item Name="BaseElements.ChangeDataUserTask9.Parameters.DataSourceFilters.Caption" Value="Data source filters" />
			<Item Name="BaseElements.ChangeDataUserTask9.Parameters.EntitySchemaUId.Caption" Value="Object" />
			<Item Name="BaseElements.ChangeDataUserTask9.Parameters.IsMatchConditions.Caption" Value="If object meets the following conditions" />
			<Item Name="BaseElements.ChangeDataUserTask9.Parameters.IsMatchConditions.DisplayValue" Value="true" />
			<Item Name="BaseElements.ChangeDataUserTask9.Parameters.RecordColumnValues.Caption" Value="Set column values" />
			<Item Name="BaseElements.ConditionalSequenceFlow1.Caption" Value="status not approved" />
			<Item Name="BaseElements.ConditionalSequenceFlow11.Caption" Value="Transfer in" />
			<Item Name="BaseElements.ConditionalSequenceFlow12.Caption" Value="Transfer out" />
			<Item Name="BaseElements.ConditionalSequenceFlow4.Caption" Value="Transfer In" />
			<Item Name="BaseElements.ConditionalSequenceFlow5.Caption" Value="Transfer in" />
			<Item Name="BaseElements.ConditionalSequenceFlow7.Caption" Value="Transfer Out" />
			<Item Name="BaseElements.ConditionalSequenceFlow9.Caption" Value="Transfer Out" />
			<Item Name="BaseElements.GlbOpenPopupWindow1.Parameters.GlbPopupWindowText.Caption" Value="Popup window text" />
			<Item Name="BaseElements.GlbOpenPopupWindow1.Parameters.GlbPopupWindowText.DisplayValue" Value="The status is not approved." />
			<Item Name="BaseElements.GlbOpenPopupWindow1.Parameters.GlbPopupWindowText.Value" Value="The status is not approved." />
			<Item Name="BaseElements.GlbOpenPopupWindow1.Parameters.GlbUserToWhomShowWindow.Caption" Value="To whom should the window be shown?" />
			<Item Name="BaseElements.GlbOpenPopupWindow1.Parameters.GlbUserToWhomShowWindow.DisplayValue" Value="[#System variable.Current user contact#]" />
			<Item Name="BaseElements.GlbOpenPopupWindow2.Parameters.GlbPopupWindowText.Caption" Value="Popup window text" />
			<Item Name="BaseElements.GlbOpenPopupWindow2.Parameters.GlbPopupWindowText.DisplayValue" Value="The status is not approved." />
			<Item Name="BaseElements.GlbOpenPopupWindow2.Parameters.GlbPopupWindowText.Value" Value="The status is not approved." />
			<Item Name="BaseElements.GlbOpenPopupWindow2.Parameters.GlbUserToWhomShowWindow.Caption" Value="To whom should the window be shown?" />
			<Item Name="BaseElements.GlbOpenPopupWindow2.Parameters.GlbUserToWhomShowWindow.DisplayValue" Value="[#System variable.Current user contact#]" />
			<Item Name="BaseElements.GlbOpenPopupWindow3.Parameters.GlbPopupWindowText.Caption" Value="Popup window text" />
			<Item Name="BaseElements.GlbOpenPopupWindow3.Parameters.GlbPopupWindowText.DisplayValue" Value="The status is not approved." />
			<Item Name="BaseElements.GlbOpenPopupWindow3.Parameters.GlbPopupWindowText.Value" Value="The status is not approved." />
			<Item Name="BaseElements.GlbOpenPopupWindow3.Parameters.GlbUserToWhomShowWindow.Caption" Value="To whom should the window be shown?" />
			<Item Name="BaseElements.GlbOpenPopupWindow3.Parameters.GlbUserToWhomShowWindow.DisplayValue" Value="[#System variable.Current user contact#]" />
			<Item Name="BaseElements.ReadDataUserTask1.Caption" Value="read request" />
			<Item Name="BaseElements.ReadDataUserTask1.Parameters.AggregationColumnName.Caption" Value="Name of aggregate function column" />
			<Item Name="BaseElements.ReadDataUserTask1.Parameters.CanReadUncommitedData.Caption" Value="Read uncommitted data" />
			<Item Name="BaseElements.ReadDataUserTask1.Parameters.ConsiderTimeInFilter.Caption" Value="Consider time in the filter" />
			<Item Name="BaseElements.ReadDataUserTask1.Parameters.ConsiderTimeInFilter.DisplayValue" Value="true" />
			<Item Name="BaseElements.ReadDataUserTask1.Parameters.DataSourceFilters.Caption" Value="Data source of filters" />
			<Item Name="BaseElements.ReadDataUserTask1.Parameters.EntityColumnMetaPathes.Caption" Value="Columns to read" />
			<Item Name="BaseElements.ReadDataUserTask1.Parameters.FunctionType.Caption" Value="Aggregate function type" />
			<Item Name="BaseElements.ReadDataUserTask1.Parameters.IgnoreDisplayValues.Caption" Value="Do not read displayed values of lookup columns" />
			<Item Name="BaseElements.ReadDataUserTask1.Parameters.NumberOfRecords.Caption" Value="Number of records to read" />
			<Item Name="BaseElements.ReadDataUserTask1.Parameters.OrderInfo.Caption" Value="Columns order" />
			<Item Name="BaseElements.ReadDataUserTask1.Parameters.ReadSomeTopRecords.Caption" Value="Read first" />
			<Item Name="BaseElements.ReadDataUserTask1.Parameters.ResultCompositeObjectList.Caption" Value="Collection of records" />
			<Item Name="BaseElements.ReadDataUserTask1.Parameters.ResultCount.Caption" Value="Number of records" />
			<Item Name="BaseElements.ReadDataUserTask1.Parameters.ResultDateTimeFunction.Caption" Value="Function result" />
			<Item Name="BaseElements.ReadDataUserTask1.Parameters.ResultEntity.Caption" Value="First item of resulting collection" />
			<Item Name="BaseElements.ReadDataUserTask1.Parameters.ResultEntityCollection.Caption" Value="Resulting collection" />
			<Item Name="BaseElements.ReadDataUserTask1.Parameters.ResultFloatFunction.Caption" Value="Function result" />
			<Item Name="BaseElements.ReadDataUserTask1.Parameters.ResultIntegerFunction.Caption" Value="Function result" />
			<Item Name="BaseElements.ReadDataUserTask1.Parameters.ResultRowsCount.Caption" Value="Number of records read" />
			<Item Name="BaseElements.ReadDataUserTask1.Parameters.ResultType.Caption" Value="Type of result" />
			<Item Name="BaseElements.ReadDataUserTask10.Caption" Value="read source marketing fund" />
			<Item Name="BaseElements.ReadDataUserTask10.Parameters.AggregationColumnName.Caption" Value="Name of aggregate function column" />
			<Item Name="BaseElements.ReadDataUserTask10.Parameters.CanReadUncommitedData.Caption" Value="Read uncommitted data" />
			<Item Name="BaseElements.ReadDataUserTask10.Parameters.ConsiderTimeInFilter.Caption" Value="Consider time in the filter" />
			<Item Name="BaseElements.ReadDataUserTask10.Parameters.ConsiderTimeInFilter.DisplayValue" Value="true" />
			<Item Name="BaseElements.ReadDataUserTask10.Parameters.DataSourceFilters.Caption" Value="Data source of filters" />
			<Item Name="BaseElements.ReadDataUserTask10.Parameters.EntityColumnMetaPathes.Caption" Value="Columns to read" />
			<Item Name="BaseElements.ReadDataUserTask10.Parameters.FunctionType.Caption" Value="Aggregate function type" />
			<Item Name="BaseElements.ReadDataUserTask10.Parameters.IgnoreDisplayValues.Caption" Value="Do not read displayed values of lookup columns" />
			<Item Name="BaseElements.ReadDataUserTask10.Parameters.NumberOfRecords.Caption" Value="Number of records to read" />
			<Item Name="BaseElements.ReadDataUserTask10.Parameters.OrderInfo.Caption" Value="Columns order" />
			<Item Name="BaseElements.ReadDataUserTask10.Parameters.ReadSomeTopRecords.Caption" Value="Read first" />
			<Item Name="BaseElements.ReadDataUserTask10.Parameters.ResultCompositeObjectList.Caption" Value="Collection of records" />
			<Item Name="BaseElements.ReadDataUserTask10.Parameters.ResultCount.Caption" Value="Number of records" />
			<Item Name="BaseElements.ReadDataUserTask10.Parameters.ResultDateTimeFunction.Caption" Value="Function result" />
			<Item Name="BaseElements.ReadDataUserTask10.Parameters.ResultEntity.Caption" Value="First item of resulting collection" />
			<Item Name="BaseElements.ReadDataUserTask10.Parameters.ResultEntityCollection.Caption" Value="Resulting collection" />
			<Item Name="BaseElements.ReadDataUserTask10.Parameters.ResultFloatFunction.Caption" Value="Function result" />
			<Item Name="BaseElements.ReadDataUserTask10.Parameters.ResultIntegerFunction.Caption" Value="Function result" />
			<Item Name="BaseElements.ReadDataUserTask10.Parameters.ResultRowsCount.Caption" Value="Number of records read" />
			<Item Name="BaseElements.ReadDataUserTask10.Parameters.ResultType.Caption" Value="Type of result" />
			<Item Name="BaseElements.ReadDataUserTask11.Caption" Value="marketing fund detail combine" />
			<Item Name="BaseElements.ReadDataUserTask11.Parameters.AggregationColumnName.Caption" Value="Name of aggregate function column" />
			<Item Name="BaseElements.ReadDataUserTask11.Parameters.CanReadUncommitedData.Caption" Value="Read uncommitted data" />
			<Item Name="BaseElements.ReadDataUserTask11.Parameters.ConsiderTimeInFilter.Caption" Value="Consider time in the filter" />
			<Item Name="BaseElements.ReadDataUserTask11.Parameters.ConsiderTimeInFilter.DisplayValue" Value="true" />
			<Item Name="BaseElements.ReadDataUserTask11.Parameters.DataSourceFilters.Caption" Value="Data source of filters" />
			<Item Name="BaseElements.ReadDataUserTask11.Parameters.EntityColumnMetaPathes.Caption" Value="Columns to read" />
			<Item Name="BaseElements.ReadDataUserTask11.Parameters.FunctionType.Caption" Value="Aggregate function type" />
			<Item Name="BaseElements.ReadDataUserTask11.Parameters.IgnoreDisplayValues.Caption" Value="Do not read displayed values of lookup columns" />
			<Item Name="BaseElements.ReadDataUserTask11.Parameters.NumberOfRecords.Caption" Value="Number of records to read" />
			<Item Name="BaseElements.ReadDataUserTask11.Parameters.OrderInfo.Caption" Value="Columns order" />
			<Item Name="BaseElements.ReadDataUserTask11.Parameters.ReadSomeTopRecords.Caption" Value="Read first" />
			<Item Name="BaseElements.ReadDataUserTask11.Parameters.ResultCompositeObjectList.AMDAMDPosting.Caption" Value="Posting" />
			<Item Name="BaseElements.ReadDataUserTask11.Parameters.ResultCompositeObjectList.AMDInitialAmount.Caption" Value="Initial Amount" />
			<Item Name="BaseElements.ReadDataUserTask11.Parameters.ResultCompositeObjectList.AMDMarketingFund.Caption" Value="Marketing Funds" />
			<Item Name="BaseElements.ReadDataUserTask11.Parameters.ResultCompositeObjectList.AMDName.Caption" Value="Name" />
			<Item Name="BaseElements.ReadDataUserTask11.Parameters.ResultCompositeObjectList.AMDRequest.Caption" Value="Request" />
			<Item Name="BaseElements.ReadDataUserTask11.Parameters.ResultCompositeObjectList.AMDTransferAmount.Caption" Value="Transfer Amount" />
			<Item Name="BaseElements.ReadDataUserTask11.Parameters.ResultCompositeObjectList.Caption" Value="Collection of records" />
			<Item Name="BaseElements.ReadDataUserTask11.Parameters.ResultCount.Caption" Value="Number of records" />
			<Item Name="BaseElements.ReadDataUserTask11.Parameters.ResultDateTimeFunction.Caption" Value="Function result" />
			<Item Name="BaseElements.ReadDataUserTask11.Parameters.ResultEntity.Caption" Value="First item of resulting collection" />
			<Item Name="BaseElements.ReadDataUserTask11.Parameters.ResultEntityCollection.Caption" Value="Resulting collection" />
			<Item Name="BaseElements.ReadDataUserTask11.Parameters.ResultFloatFunction.Caption" Value="Function result" />
			<Item Name="BaseElements.ReadDataUserTask11.Parameters.ResultIntegerFunction.Caption" Value="Function result" />
			<Item Name="BaseElements.ReadDataUserTask11.Parameters.ResultRowsCount.Caption" Value="Number of records read" />
			<Item Name="BaseElements.ReadDataUserTask11.Parameters.ResultType.Caption" Value="Type of result" />
			<Item Name="BaseElements.ReadDataUserTask12.Caption" Value="Read top mfund" />
			<Item Name="BaseElements.ReadDataUserTask12.Parameters.AggregationColumnName.Caption" Value="Name of aggregate function column" />
			<Item Name="BaseElements.ReadDataUserTask12.Parameters.CanReadUncommitedData.Caption" Value="Read uncommitted data" />
			<Item Name="BaseElements.ReadDataUserTask12.Parameters.ConsiderTimeInFilter.Caption" Value="Consider time in the filter" />
			<Item Name="BaseElements.ReadDataUserTask12.Parameters.ConsiderTimeInFilter.DisplayValue" Value="true" />
			<Item Name="BaseElements.ReadDataUserTask12.Parameters.DataSourceFilters.Caption" Value="Data source of filters" />
			<Item Name="BaseElements.ReadDataUserTask12.Parameters.EntityColumnMetaPathes.Caption" Value="Columns to read" />
			<Item Name="BaseElements.ReadDataUserTask12.Parameters.FunctionType.Caption" Value="Aggregate function type" />
			<Item Name="BaseElements.ReadDataUserTask12.Parameters.IgnoreDisplayValues.Caption" Value="Do not read displayed values of lookup columns" />
			<Item Name="BaseElements.ReadDataUserTask12.Parameters.NumberOfRecords.Caption" Value="Number of records to read" />
			<Item Name="BaseElements.ReadDataUserTask12.Parameters.OrderInfo.Caption" Value="Columns order" />
			<Item Name="BaseElements.ReadDataUserTask12.Parameters.ReadSomeTopRecords.Caption" Value="Read first" />
			<Item Name="BaseElements.ReadDataUserTask12.Parameters.ResultCompositeObjectList.Caption" Value="Collection of records" />
			<Item Name="BaseElements.ReadDataUserTask12.Parameters.ResultCount.Caption" Value="Number of records" />
			<Item Name="BaseElements.ReadDataUserTask12.Parameters.ResultDateTimeFunction.Caption" Value="Function result" />
			<Item Name="BaseElements.ReadDataUserTask12.Parameters.ResultEntity.Caption" Value="First item of resulting collection" />
			<Item Name="BaseElements.ReadDataUserTask12.Parameters.ResultEntityCollection.Caption" Value="Resulting collection" />
			<Item Name="BaseElements.ReadDataUserTask12.Parameters.ResultFloatFunction.Caption" Value="Function result" />
			<Item Name="BaseElements.ReadDataUserTask12.Parameters.ResultIntegerFunction.Caption" Value="Function result" />
			<Item Name="BaseElements.ReadDataUserTask12.Parameters.ResultRowsCount.Caption" Value="Number of records read" />
			<Item Name="BaseElements.ReadDataUserTask12.Parameters.ResultType.Caption" Value="Type of result" />
			<Item Name="BaseElements.ReadDataUserTask13.Caption" Value="Total transfer amnt-mfund" />
			<Item Name="BaseElements.ReadDataUserTask13.Parameters.AggregationColumnName.Caption" Value="Name of aggregate function column" />
			<Item Name="BaseElements.ReadDataUserTask13.Parameters.CanReadUncommitedData.Caption" Value="Read uncommitted data" />
			<Item Name="BaseElements.ReadDataUserTask13.Parameters.ConsiderTimeInFilter.Caption" Value="Consider time in the filter" />
			<Item Name="BaseElements.ReadDataUserTask13.Parameters.ConsiderTimeInFilter.DisplayValue" Value="true" />
			<Item Name="BaseElements.ReadDataUserTask13.Parameters.DataSourceFilters.Caption" Value="Data source of filters" />
			<Item Name="BaseElements.ReadDataUserTask13.Parameters.EntityColumnMetaPathes.Caption" Value="Columns to read" />
			<Item Name="BaseElements.ReadDataUserTask13.Parameters.FunctionType.Caption" Value="Aggregate function type" />
			<Item Name="BaseElements.ReadDataUserTask13.Parameters.IgnoreDisplayValues.Caption" Value="Do not read displayed values of lookup columns" />
			<Item Name="BaseElements.ReadDataUserTask13.Parameters.NumberOfRecords.Caption" Value="Number of records to read" />
			<Item Name="BaseElements.ReadDataUserTask13.Parameters.OrderInfo.Caption" Value="Columns order" />
			<Item Name="BaseElements.ReadDataUserTask13.Parameters.ReadSomeTopRecords.Caption" Value="Read first" />
			<Item Name="BaseElements.ReadDataUserTask13.Parameters.ResultCompositeObjectList.Caption" Value="Collection of records" />
			<Item Name="BaseElements.ReadDataUserTask13.Parameters.ResultCount.Caption" Value="Number of records" />
			<Item Name="BaseElements.ReadDataUserTask13.Parameters.ResultDateTimeFunction.Caption" Value="Function result" />
			<Item Name="BaseElements.ReadDataUserTask13.Parameters.ResultEntity.Caption" Value="First item of resulting collection" />
			<Item Name="BaseElements.ReadDataUserTask13.Parameters.ResultEntityCollection.Caption" Value="Resulting collection" />
			<Item Name="BaseElements.ReadDataUserTask13.Parameters.ResultFloatFunction.Caption" Value="Function result" />
			<Item Name="BaseElements.ReadDataUserTask13.Parameters.ResultIntegerFunction.Caption" Value="Function result" />
			<Item Name="BaseElements.ReadDataUserTask13.Parameters.ResultRowsCount.Caption" Value="Number of records read" />
			<Item Name="BaseElements.ReadDataUserTask13.Parameters.ResultType.Caption" Value="Type of result" />
			<Item Name="BaseElements.ReadDataUserTask14.Caption" Value="Read top SR" />
			<Item Name="BaseElements.ReadDataUserTask14.Parameters.AggregationColumnName.Caption" Value="Name of aggregate function column" />
			<Item Name="BaseElements.ReadDataUserTask14.Parameters.CanReadUncommitedData.Caption" Value="Read uncommitted data" />
			<Item Name="BaseElements.ReadDataUserTask14.Parameters.ConsiderTimeInFilter.Caption" Value="Consider time in the filter" />
			<Item Name="BaseElements.ReadDataUserTask14.Parameters.ConsiderTimeInFilter.DisplayValue" Value="true" />
			<Item Name="BaseElements.ReadDataUserTask14.Parameters.DataSourceFilters.Caption" Value="Data source of filters" />
			<Item Name="BaseElements.ReadDataUserTask14.Parameters.EntityColumnMetaPathes.Caption" Value="Columns to read" />
			<Item Name="BaseElements.ReadDataUserTask14.Parameters.FunctionType.Caption" Value="Aggregate function type" />
			<Item Name="BaseElements.ReadDataUserTask14.Parameters.IgnoreDisplayValues.Caption" Value="Do not read displayed values of lookup columns" />
			<Item Name="BaseElements.ReadDataUserTask14.Parameters.NumberOfRecords.Caption" Value="Number of records to read" />
			<Item Name="BaseElements.ReadDataUserTask14.Parameters.OrderInfo.Caption" Value="Columns order" />
			<Item Name="BaseElements.ReadDataUserTask14.Parameters.ReadSomeTopRecords.Caption" Value="Read first" />
			<Item Name="BaseElements.ReadDataUserTask14.Parameters.ResultCompositeObjectList.Caption" Value="Collection of records" />
			<Item Name="BaseElements.ReadDataUserTask14.Parameters.ResultCount.Caption" Value="Number of records" />
			<Item Name="BaseElements.ReadDataUserTask14.Parameters.ResultDateTimeFunction.Caption" Value="Function result" />
			<Item Name="BaseElements.ReadDataUserTask14.Parameters.ResultEntity.Caption" Value="First item of resulting collection" />
			<Item Name="BaseElements.ReadDataUserTask14.Parameters.ResultEntityCollection.Caption" Value="Resulting collection" />
			<Item Name="BaseElements.ReadDataUserTask14.Parameters.ResultFloatFunction.Caption" Value="Function result" />
			<Item Name="BaseElements.ReadDataUserTask14.Parameters.ResultIntegerFunction.Caption" Value="Function result" />
			<Item Name="BaseElements.ReadDataUserTask14.Parameters.ResultRowsCount.Caption" Value="Number of records read" />
			<Item Name="BaseElements.ReadDataUserTask14.Parameters.ResultType.Caption" Value="Type of result" />
			<Item Name="BaseElements.ReadDataUserTask2.Caption" Value="Read source regional budget" />
			<Item Name="BaseElements.ReadDataUserTask2.Parameters.AggregationColumnName.Caption" Value="Name of aggregate function column" />
			<Item Name="BaseElements.ReadDataUserTask2.Parameters.CanReadUncommitedData.Caption" Value="Read uncommitted data" />
			<Item Name="BaseElements.ReadDataUserTask2.Parameters.ConsiderTimeInFilter.Caption" Value="Consider time in the filter" />
			<Item Name="BaseElements.ReadDataUserTask2.Parameters.ConsiderTimeInFilter.DisplayValue" Value="true" />
			<Item Name="BaseElements.ReadDataUserTask2.Parameters.DataSourceFilters.Caption" Value="Data source of filters" />
			<Item Name="BaseElements.ReadDataUserTask2.Parameters.EntityColumnMetaPathes.Caption" Value="Columns to read" />
			<Item Name="BaseElements.ReadDataUserTask2.Parameters.FunctionType.Caption" Value="Aggregate function type" />
			<Item Name="BaseElements.ReadDataUserTask2.Parameters.IgnoreDisplayValues.Caption" Value="Do not read displayed values of lookup columns" />
			<Item Name="BaseElements.ReadDataUserTask2.Parameters.NumberOfRecords.Caption" Value="Number of records to read" />
			<Item Name="BaseElements.ReadDataUserTask2.Parameters.OrderInfo.Caption" Value="Columns order" />
			<Item Name="BaseElements.ReadDataUserTask2.Parameters.ReadSomeTopRecords.Caption" Value="Read first" />
			<Item Name="BaseElements.ReadDataUserTask2.Parameters.ResultCompositeObjectList.Caption" Value="Collection of records" />
			<Item Name="BaseElements.ReadDataUserTask2.Parameters.ResultCount.Caption" Value="Number of records" />
			<Item Name="BaseElements.ReadDataUserTask2.Parameters.ResultDateTimeFunction.Caption" Value="Function result" />
			<Item Name="BaseElements.ReadDataUserTask2.Parameters.ResultEntity.Caption" Value="First item of resulting collection" />
			<Item Name="BaseElements.ReadDataUserTask2.Parameters.ResultEntityCollection.Caption" Value="Resulting collection" />
			<Item Name="BaseElements.ReadDataUserTask2.Parameters.ResultFloatFunction.Caption" Value="Function result" />
			<Item Name="BaseElements.ReadDataUserTask2.Parameters.ResultIntegerFunction.Caption" Value="Function result" />
			<Item Name="BaseElements.ReadDataUserTask2.Parameters.ResultRowsCount.Caption" Value="Number of records read" />
			<Item Name="BaseElements.ReadDataUserTask2.Parameters.ResultType.Caption" Value="Type of result" />
			<Item Name="BaseElements.ReadDataUserTask3.Caption" Value="Read source sub regional budget" />
			<Item Name="BaseElements.ReadDataUserTask3.Parameters.AggregationColumnName.Caption" Value="Name of aggregate function column" />
			<Item Name="BaseElements.ReadDataUserTask3.Parameters.CanReadUncommitedData.Caption" Value="Read uncommitted data" />
			<Item Name="BaseElements.ReadDataUserTask3.Parameters.ConsiderTimeInFilter.Caption" Value="Consider time in the filter" />
			<Item Name="BaseElements.ReadDataUserTask3.Parameters.ConsiderTimeInFilter.DisplayValue" Value="true" />
			<Item Name="BaseElements.ReadDataUserTask3.Parameters.DataSourceFilters.Caption" Value="Data source of filters" />
			<Item Name="BaseElements.ReadDataUserTask3.Parameters.EntityColumnMetaPathes.Caption" Value="Columns to read" />
			<Item Name="BaseElements.ReadDataUserTask3.Parameters.FunctionType.Caption" Value="Aggregate function type" />
			<Item Name="BaseElements.ReadDataUserTask3.Parameters.IgnoreDisplayValues.Caption" Value="Do not read displayed values of lookup columns" />
			<Item Name="BaseElements.ReadDataUserTask3.Parameters.NumberOfRecords.Caption" Value="Number of records to read" />
			<Item Name="BaseElements.ReadDataUserTask3.Parameters.OrderInfo.Caption" Value="Columns order" />
			<Item Name="BaseElements.ReadDataUserTask3.Parameters.ReadSomeTopRecords.Caption" Value="Read first" />
			<Item Name="BaseElements.ReadDataUserTask3.Parameters.ResultCompositeObjectList.Caption" Value="Collection of records" />
			<Item Name="BaseElements.ReadDataUserTask3.Parameters.ResultCount.Caption" Value="Number of records" />
			<Item Name="BaseElements.ReadDataUserTask3.Parameters.ResultDateTimeFunction.Caption" Value="Function result" />
			<Item Name="BaseElements.ReadDataUserTask3.Parameters.ResultEntity.Caption" Value="First item of resulting collection" />
			<Item Name="BaseElements.ReadDataUserTask3.Parameters.ResultEntityCollection.Caption" Value="Resulting collection" />
			<Item Name="BaseElements.ReadDataUserTask3.Parameters.ResultFloatFunction.Caption" Value="Function result" />
			<Item Name="BaseElements.ReadDataUserTask3.Parameters.ResultIntegerFunction.Caption" Value="Function result" />
			<Item Name="BaseElements.ReadDataUserTask3.Parameters.ResultRowsCount.Caption" Value="Number of records read" />
			<Item Name="BaseElements.ReadDataUserTask3.Parameters.ResultType.Caption" Value="Type of result" />
			<Item Name="BaseElements.ReadDataUserTask5.Caption" Value="sub region budget detail combine" />
			<Item Name="BaseElements.ReadDataUserTask5.Parameters.AggregationColumnName.Caption" Value="Name of aggregate function column" />
			<Item Name="BaseElements.ReadDataUserTask5.Parameters.CanReadUncommitedData.Caption" Value="Read uncommitted data" />
			<Item Name="BaseElements.ReadDataUserTask5.Parameters.ConsiderTimeInFilter.Caption" Value="Consider time in the filter" />
			<Item Name="BaseElements.ReadDataUserTask5.Parameters.ConsiderTimeInFilter.DisplayValue" Value="true" />
			<Item Name="BaseElements.ReadDataUserTask5.Parameters.DataSourceFilters.Caption" Value="Data source of filters" />
			<Item Name="BaseElements.ReadDataUserTask5.Parameters.EntityColumnMetaPathes.Caption" Value="Columns to read" />
			<Item Name="BaseElements.ReadDataUserTask5.Parameters.FunctionType.Caption" Value="Aggregate function type" />
			<Item Name="BaseElements.ReadDataUserTask5.Parameters.IgnoreDisplayValues.Caption" Value="Do not read displayed values of lookup columns" />
			<Item Name="BaseElements.ReadDataUserTask5.Parameters.NumberOfRecords.Caption" Value="Number of records to read" />
			<Item Name="BaseElements.ReadDataUserTask5.Parameters.OrderInfo.Caption" Value="Columns order" />
			<Item Name="BaseElements.ReadDataUserTask5.Parameters.ReadSomeTopRecords.Caption" Value="Read first" />
			<Item Name="BaseElements.ReadDataUserTask5.Parameters.ResultCompositeObjectList.AMDAMDPosting.Caption" Value="Posting" />
			<Item Name="BaseElements.ReadDataUserTask5.Parameters.ResultCompositeObjectList.AMDInitialAmount.Caption" Value="Initial Amount" />
			<Item Name="BaseElements.ReadDataUserTask5.Parameters.ResultCompositeObjectList.AMDName.Caption" Value="Name" />
			<Item Name="BaseElements.ReadDataUserTask5.Parameters.ResultCompositeObjectList.AMDRequest.Caption" Value="Request" />
			<Item Name="BaseElements.ReadDataUserTask5.Parameters.ResultCompositeObjectList.AMDSubRegionalDistribution.Caption" Value="Sub Regional distrbution" />
			<Item Name="BaseElements.ReadDataUserTask5.Parameters.ResultCompositeObjectList.AMDTransferAmount.Caption" Value="Transfer Amount" />
			<Item Name="BaseElements.ReadDataUserTask5.Parameters.ResultCompositeObjectList.Caption" Value="Collection of records" />
			<Item Name="BaseElements.ReadDataUserTask5.Parameters.ResultCount.Caption" Value="Number of records" />
			<Item Name="BaseElements.ReadDataUserTask5.Parameters.ResultDateTimeFunction.Caption" Value="Function result" />
			<Item Name="BaseElements.ReadDataUserTask5.Parameters.ResultEntity.Caption" Value="First item of resulting collection" />
			<Item Name="BaseElements.ReadDataUserTask5.Parameters.ResultEntityCollection.Caption" Value="Resulting collection" />
			<Item Name="BaseElements.ReadDataUserTask5.Parameters.ResultFloatFunction.Caption" Value="Function result" />
			<Item Name="BaseElements.ReadDataUserTask5.Parameters.ResultIntegerFunction.Caption" Value="Function result" />
			<Item Name="BaseElements.ReadDataUserTask5.Parameters.ResultRowsCount.Caption" Value="Number of records read" />
			<Item Name="BaseElements.ReadDataUserTask5.Parameters.ResultType.Caption" Value="Type of result" />
			<Item Name="BaseElements.ReadDataUserTask6.Caption" Value="region budget detail combine" />
			<Item Name="BaseElements.ReadDataUserTask6.Parameters.AggregationColumnName.Caption" Value="Name of aggregate function column" />
			<Item Name="BaseElements.ReadDataUserTask6.Parameters.CanReadUncommitedData.Caption" Value="Read uncommitted data" />
			<Item Name="BaseElements.ReadDataUserTask6.Parameters.ConsiderTimeInFilter.Caption" Value="Consider time in the filter" />
			<Item Name="BaseElements.ReadDataUserTask6.Parameters.ConsiderTimeInFilter.DisplayValue" Value="true" />
			<Item Name="BaseElements.ReadDataUserTask6.Parameters.DataSourceFilters.Caption" Value="Data source of filters" />
			<Item Name="BaseElements.ReadDataUserTask6.Parameters.EntityColumnMetaPathes.Caption" Value="Columns to read" />
			<Item Name="BaseElements.ReadDataUserTask6.Parameters.FunctionType.Caption" Value="Aggregate function type" />
			<Item Name="BaseElements.ReadDataUserTask6.Parameters.IgnoreDisplayValues.Caption" Value="Do not read displayed values of lookup columns" />
			<Item Name="BaseElements.ReadDataUserTask6.Parameters.NumberOfRecords.Caption" Value="Number of records to read" />
			<Item Name="BaseElements.ReadDataUserTask6.Parameters.OrderInfo.Caption" Value="Columns order" />
			<Item Name="BaseElements.ReadDataUserTask6.Parameters.ReadSomeTopRecords.Caption" Value="Read first" />
			<Item Name="BaseElements.ReadDataUserTask6.Parameters.ResultCompositeObjectList.AMDAccountingClassification.Caption" Value="Accounting Classification" />
			<Item Name="BaseElements.ReadDataUserTask6.Parameters.ResultCompositeObjectList.AMDFinalAmount.Caption" Value="Final Amount" />
			<Item Name="BaseElements.ReadDataUserTask6.Parameters.ResultCompositeObjectList.AMDInitialAmount.Caption" Value="Initial Amount" />
			<Item Name="BaseElements.ReadDataUserTask6.Parameters.ResultCompositeObjectList.AMDMarketingFunds.Caption" Value="Marketing Funds" />
			<Item Name="BaseElements.ReadDataUserTask6.Parameters.ResultCompositeObjectList.AMDName.Caption" Value="Name" />
			<Item Name="BaseElements.ReadDataUserTask6.Parameters.ResultCompositeObjectList.AMDPosting.Caption" Value="Posting" />
			<Item Name="BaseElements.ReadDataUserTask6.Parameters.ResultCompositeObjectList.AMDRegionalBudget.Caption" Value="Regional Budget" />
			<Item Name="BaseElements.ReadDataUserTask6.Parameters.ResultCompositeObjectList.AMDRequest.Caption" Value="Request" />
			<Item Name="BaseElements.ReadDataUserTask6.Parameters.ResultCompositeObjectList.AMDSubRegionalDistribution.Caption" Value="Sub Regional Distribution" />
			<Item Name="BaseElements.ReadDataUserTask6.Parameters.ResultCompositeObjectList.AMDTransferAmount.Caption" Value="Transfer Amount" />
			<Item Name="BaseElements.ReadDataUserTask6.Parameters.ResultCompositeObjectList.Caption" Value="Collection of records" />
			<Item Name="BaseElements.ReadDataUserTask6.Parameters.ResultCompositeObjectList.CreatedBy.Caption" Value="Created by" />
			<Item Name="BaseElements.ReadDataUserTask6.Parameters.ResultCompositeObjectList.CreatedOn.Caption" Value="Created on" />
			<Item Name="BaseElements.ReadDataUserTask6.Parameters.ResultCompositeObjectList.Id.Caption" Value="Id" />
			<Item Name="BaseElements.ReadDataUserTask6.Parameters.ResultCompositeObjectList.ModifiedBy.Caption" Value="Modified by" />
			<Item Name="BaseElements.ReadDataUserTask6.Parameters.ResultCompositeObjectList.ModifiedOn.Caption" Value="Modified on" />
			<Item Name="BaseElements.ReadDataUserTask6.Parameters.ResultCompositeObjectList.ProcessListeners.Caption" Value="Active processes" />
			<Item Name="BaseElements.ReadDataUserTask6.Parameters.ResultCount.Caption" Value="Number of records" />
			<Item Name="BaseElements.ReadDataUserTask6.Parameters.ResultDateTimeFunction.Caption" Value="Function result" />
			<Item Name="BaseElements.ReadDataUserTask6.Parameters.ResultEntity.Caption" Value="First item of resulting collection" />
			<Item Name="BaseElements.ReadDataUserTask6.Parameters.ResultEntityCollection.Caption" Value="Resulting collection" />
			<Item Name="BaseElements.ReadDataUserTask6.Parameters.ResultFloatFunction.Caption" Value="Function result" />
			<Item Name="BaseElements.ReadDataUserTask6.Parameters.ResultIntegerFunction.Caption" Value="Function result" />
			<Item Name="BaseElements.ReadDataUserTask6.Parameters.ResultRowsCount.Caption" Value="Number of records read" />
			<Item Name="BaseElements.ReadDataUserTask6.Parameters.ResultType.Caption" Value="Type of result" />
			<Item Name="BaseElements.ReadDataUserTask7.Caption" Value="Read top RB" />
			<Item Name="BaseElements.ReadDataUserTask7.Parameters.AggregationColumnName.Caption" Value="Name of aggregate function column" />
			<Item Name="BaseElements.ReadDataUserTask7.Parameters.CanReadUncommitedData.Caption" Value="Read uncommitted data" />
			<Item Name="BaseElements.ReadDataUserTask7.Parameters.ConsiderTimeInFilter.Caption" Value="Consider time in the filter" />
			<Item Name="BaseElements.ReadDataUserTask7.Parameters.ConsiderTimeInFilter.DisplayValue" Value="true" />
			<Item Name="BaseElements.ReadDataUserTask7.Parameters.DataSourceFilters.Caption" Value="Data source of filters" />
			<Item Name="BaseElements.ReadDataUserTask7.Parameters.EntityColumnMetaPathes.Caption" Value="Columns to read" />
			<Item Name="BaseElements.ReadDataUserTask7.Parameters.FunctionType.Caption" Value="Aggregate function type" />
			<Item Name="BaseElements.ReadDataUserTask7.Parameters.IgnoreDisplayValues.Caption" Value="Do not read displayed values of lookup columns" />
			<Item Name="BaseElements.ReadDataUserTask7.Parameters.NumberOfRecords.Caption" Value="Number of records to read" />
			<Item Name="BaseElements.ReadDataUserTask7.Parameters.OrderInfo.Caption" Value="Columns order" />
			<Item Name="BaseElements.ReadDataUserTask7.Parameters.ReadSomeTopRecords.Caption" Value="Read first" />
			<Item Name="BaseElements.ReadDataUserTask7.Parameters.ResultCompositeObjectList.Caption" Value="Collection of records" />
			<Item Name="BaseElements.ReadDataUserTask7.Parameters.ResultCount.Caption" Value="Number of records" />
			<Item Name="BaseElements.ReadDataUserTask7.Parameters.ResultDateTimeFunction.Caption" Value="Function result" />
			<Item Name="BaseElements.ReadDataUserTask7.Parameters.ResultEntity.Caption" Value="First item of resulting collection" />
			<Item Name="BaseElements.ReadDataUserTask7.Parameters.ResultEntityCollection.Caption" Value="Resulting collection" />
			<Item Name="BaseElements.ReadDataUserTask7.Parameters.ResultFloatFunction.Caption" Value="Function result" />
			<Item Name="BaseElements.ReadDataUserTask7.Parameters.ResultIntegerFunction.Caption" Value="Function result" />
			<Item Name="BaseElements.ReadDataUserTask7.Parameters.ResultRowsCount.Caption" Value="Number of records read" />
			<Item Name="BaseElements.ReadDataUserTask7.Parameters.ResultType.Caption" Value="Type of result" />
			<Item Name="BaseElements.ReadDataUserTask8.Caption" Value="Total transfer amount" />
			<Item Name="BaseElements.ReadDataUserTask8.Parameters.AggregationColumnName.Caption" Value="Name of aggregate function column" />
			<Item Name="BaseElements.ReadDataUserTask8.Parameters.CanReadUncommitedData.Caption" Value="Read uncommitted data" />
			<Item Name="BaseElements.ReadDataUserTask8.Parameters.ConsiderTimeInFilter.Caption" Value="Consider time in the filter" />
			<Item Name="BaseElements.ReadDataUserTask8.Parameters.ConsiderTimeInFilter.DisplayValue" Value="true" />
			<Item Name="BaseElements.ReadDataUserTask8.Parameters.DataSourceFilters.Caption" Value="Data source of filters" />
			<Item Name="BaseElements.ReadDataUserTask8.Parameters.EntityColumnMetaPathes.Caption" Value="Columns to read" />
			<Item Name="BaseElements.ReadDataUserTask8.Parameters.FunctionType.Caption" Value="Aggregate function type" />
			<Item Name="BaseElements.ReadDataUserTask8.Parameters.IgnoreDisplayValues.Caption" Value="Do not read displayed values of lookup columns" />
			<Item Name="BaseElements.ReadDataUserTask8.Parameters.NumberOfRecords.Caption" Value="Number of records to read" />
			<Item Name="BaseElements.ReadDataUserTask8.Parameters.OrderInfo.Caption" Value="Columns order" />
			<Item Name="BaseElements.ReadDataUserTask8.Parameters.ReadSomeTopRecords.Caption" Value="Read first" />
			<Item Name="BaseElements.ReadDataUserTask8.Parameters.ResultCompositeObjectList.Caption" Value="Collection of records" />
			<Item Name="BaseElements.ReadDataUserTask8.Parameters.ResultCount.Caption" Value="Number of records" />
			<Item Name="BaseElements.ReadDataUserTask8.Parameters.ResultDateTimeFunction.Caption" Value="Function result" />
			<Item Name="BaseElements.ReadDataUserTask8.Parameters.ResultEntity.Caption" Value="First item of resulting collection" />
			<Item Name="BaseElements.ReadDataUserTask8.Parameters.ResultEntityCollection.Caption" Value="Resulting collection" />
			<Item Name="BaseElements.ReadDataUserTask8.Parameters.ResultFloatFunction.Caption" Value="Function result" />
			<Item Name="BaseElements.ReadDataUserTask8.Parameters.ResultIntegerFunction.Caption" Value="Function result" />
			<Item Name="BaseElements.ReadDataUserTask8.Parameters.ResultRowsCount.Caption" Value="Number of records read" />
			<Item Name="BaseElements.ReadDataUserTask8.Parameters.ResultType.Caption" Value="Type of result" />
			<Item Name="BaseElements.ReadDataUserTask9.Caption" Value="Total transfr amount SR" />
			<Item Name="BaseElements.ReadDataUserTask9.Parameters.AggregationColumnName.Caption" Value="Name of aggregate function column" />
			<Item Name="BaseElements.ReadDataUserTask9.Parameters.CanReadUncommitedData.Caption" Value="Read uncommitted data" />
			<Item Name="BaseElements.ReadDataUserTask9.Parameters.ConsiderTimeInFilter.Caption" Value="Consider time in the filter" />
			<Item Name="BaseElements.ReadDataUserTask9.Parameters.ConsiderTimeInFilter.DisplayValue" Value="true" />
			<Item Name="BaseElements.ReadDataUserTask9.Parameters.DataSourceFilters.Caption" Value="Data source of filters" />
			<Item Name="BaseElements.ReadDataUserTask9.Parameters.EntityColumnMetaPathes.Caption" Value="Columns to read" />
			<Item Name="BaseElements.ReadDataUserTask9.Parameters.FunctionType.Caption" Value="Aggregate function type" />
			<Item Name="BaseElements.ReadDataUserTask9.Parameters.IgnoreDisplayValues.Caption" Value="Do not read displayed values of lookup columns" />
			<Item Name="BaseElements.ReadDataUserTask9.Parameters.NumberOfRecords.Caption" Value="Number of records to read" />
			<Item Name="BaseElements.ReadDataUserTask9.Parameters.OrderInfo.Caption" Value="Columns order" />
			<Item Name="BaseElements.ReadDataUserTask9.Parameters.ReadSomeTopRecords.Caption" Value="Read first" />
			<Item Name="BaseElements.ReadDataUserTask9.Parameters.ResultCompositeObjectList.Caption" Value="Collection of records" />
			<Item Name="BaseElements.ReadDataUserTask9.Parameters.ResultCount.Caption" Value="Number of records" />
			<Item Name="BaseElements.ReadDataUserTask9.Parameters.ResultDateTimeFunction.Caption" Value="Function result" />
			<Item Name="BaseElements.ReadDataUserTask9.Parameters.ResultEntity.Caption" Value="First item of resulting collection" />
			<Item Name="BaseElements.ReadDataUserTask9.Parameters.ResultEntityCollection.Caption" Value="Resulting collection" />
			<Item Name="BaseElements.ReadDataUserTask9.Parameters.ResultFloatFunction.Caption" Value="Function result" />
			<Item Name="BaseElements.ReadDataUserTask9.Parameters.ResultIntegerFunction.Caption" Value="Function result" />
			<Item Name="BaseElements.ReadDataUserTask9.Parameters.ResultRowsCount.Caption" Value="Number of records read" />
			<Item Name="BaseElements.ReadDataUserTask9.Parameters.ResultType.Caption" Value="Type of result" />
			<Item Name="BaseElements.SubProcess1.Caption" Value="Transfer amount SubRegional Budget 1" />
			<Item Name="BaseElements.SubProcess1.Parameters.CompletedIterationsCount.Caption" Value="Number of completed instances" />
			<Item Name="BaseElements.SubProcess1.Parameters.InputRecordCollection.Caption" Value="Input record collection" />
			<Item Name="BaseElements.SubProcess1.Parameters.InputRecordCollection.DisplayValue" Value="[#sub region budget detail combine.Collection of records#]" />
			<Item Name="BaseElements.SubProcess1.Parameters.InputRecordCollection.MktgFunds.Caption" Value="MktgFunds" />
			<Item Name="BaseElements.SubProcess1.Parameters.InputRecordCollection.Request.Caption" Value="Request" />
			<Item Name="BaseElements.SubProcess1.Parameters.InputRecordCollection.Request.DisplayValue" Value="[#read request.First item of resulting collection.Id#]" />
			<Item Name="BaseElements.SubProcess1.Parameters.InputRecordCollection.SubRegionalBudget.Caption" Value="SubRegionalBudget" />
			<Item Name="BaseElements.SubProcess1.Parameters.InputRecordCollection.SubRegionalBudget.DisplayValue" Value="[#sub region budget detail combine.Collection of records:Sub Regional distrbution#]" />
			<Item Name="BaseElements.SubProcess1.Parameters.InputRecordCollection.transferamount.Caption" Value="transferamount" />
			<Item Name="BaseElements.SubProcess1.Parameters.InputRecordCollection.transferamount.DisplayValue" Value="[#sub region budget detail combine.Collection of records:Transfer Amount#]" />
			<Item Name="BaseElements.SubProcess1.Parameters.OutputRecordCollection.Caption" Value="Output record collection" />
			<Item Name="BaseElements.SubProcess1.Parameters.OutputRecordCollection.MktgFunds.Caption" Value="MktgFunds" />
			<Item Name="BaseElements.SubProcess1.Parameters.OutputRecordCollection.Request.Caption" Value="Request" />
			<Item Name="BaseElements.SubProcess1.Parameters.OutputRecordCollection.SubRegionalBudget.Caption" Value="SubRegionalBudget" />
			<Item Name="BaseElements.SubProcess1.Parameters.OutputRecordCollection.transferamount.Caption" Value="transferamount" />
			<Item Name="BaseElements.SubProcess1.Parameters.TerminatedIterationsCount.Caption" Value="Number of terminated instances" />
			<Item Name="BaseElements.SubProcess1.Parameters.TotalIterationsCount.Caption" Value="Total number of instances" />
			<Item Name="BaseElements.SubProcess2.Caption" Value="Transfer amount Regional Budget 2" />
			<Item Name="BaseElements.SubProcess2.Parameters.CompletedIterationsCount.Caption" Value="Number of completed instances" />
			<Item Name="BaseElements.SubProcess2.Parameters.InputRecordCollection.Caption" Value="Input record collection" />
			<Item Name="BaseElements.SubProcess2.Parameters.InputRecordCollection.DisplayValue" Value="[#region budget detail combine.Collection of records#]" />
			<Item Name="BaseElements.SubProcess2.Parameters.InputRecordCollection.RegionalBudget.Caption" Value="RegionalBudget" />
			<Item Name="BaseElements.SubProcess2.Parameters.InputRecordCollection.RegionalBudget.DisplayValue" Value="[#region budget detail combine.Collection of records:Regional Budget#]" />
			<Item Name="BaseElements.SubProcess2.Parameters.InputRecordCollection.Request.Caption" Value="Request" />
			<Item Name="BaseElements.SubProcess2.Parameters.InputRecordCollection.Request.DisplayValue" Value="[#read request.First item of resulting collection.Id#]" />
			<Item Name="BaseElements.SubProcess2.Parameters.InputRecordCollection.SubRegion.Caption" Value="SubRegion" />
			<Item Name="BaseElements.SubProcess2.Parameters.InputRecordCollection.SubRegion.DisplayValue" Value="[#region budget detail combine.Collection of records:Sub Regional Distribution#]" />
			<Item Name="BaseElements.SubProcess2.Parameters.InputRecordCollection.transferamount.Caption" Value="transferamount" />
			<Item Name="BaseElements.SubProcess2.Parameters.InputRecordCollection.transferamount.DisplayValue" Value="[#region budget detail combine.Collection of records:Transfer Amount#]" />
			<Item Name="BaseElements.SubProcess2.Parameters.OutputRecordCollection.Caption" Value="Output record collection" />
			<Item Name="BaseElements.SubProcess2.Parameters.OutputRecordCollection.RegionalBudget.Caption" Value="RegionalBudget" />
			<Item Name="BaseElements.SubProcess2.Parameters.OutputRecordCollection.Request.Caption" Value="Request" />
			<Item Name="BaseElements.SubProcess2.Parameters.OutputRecordCollection.SubRegion.Caption" Value="SubRegion" />
			<Item Name="BaseElements.SubProcess2.Parameters.OutputRecordCollection.transferamount.Caption" Value="transferamount" />
			<Item Name="BaseElements.SubProcess2.Parameters.TerminatedIterationsCount.Caption" Value="Number of terminated instances" />
			<Item Name="BaseElements.SubProcess2.Parameters.TotalIterationsCount.Caption" Value="Total number of instances" />
			<Item Name="BaseElements.SubProcess3.Caption" Value="Transfer amount mktg fund-1" />
			<Item Name="BaseElements.SubProcess3.Parameters.CompletedIterationsCount.Caption" Value="Number of completed instances" />
			<Item Name="BaseElements.SubProcess3.Parameters.InputRecordCollection.Caption" Value="Input record collection" />
			<Item Name="BaseElements.SubProcess3.Parameters.InputRecordCollection.DisplayValue" Value="[#marketing fund detail combine.Collection of records#]" />
			<Item Name="BaseElements.SubProcess3.Parameters.InputRecordCollection.MktgFunds.Caption" Value="MktgFunds" />
			<Item Name="BaseElements.SubProcess3.Parameters.InputRecordCollection.MktgFunds.DisplayValue" Value="[#marketing fund detail combine.Collection of records:Marketing Funds#]" />
			<Item Name="BaseElements.SubProcess3.Parameters.InputRecordCollection.MktgPlans.Caption" Value="MktgPlans" />
			<Item Name="BaseElements.SubProcess3.Parameters.InputRecordCollection.Request.Caption" Value="Request" />
			<Item Name="BaseElements.SubProcess3.Parameters.InputRecordCollection.Request.DisplayValue" Value="[#read request.First item of resulting collection.Id#]" />
			<Item Name="BaseElements.SubProcess3.Parameters.InputRecordCollection.transferamount.Caption" Value="transferamount" />
			<Item Name="BaseElements.SubProcess3.Parameters.InputRecordCollection.transferamount.DisplayValue" Value="[#marketing fund detail combine.Collection of records:Transfer Amount#]" />
			<Item Name="BaseElements.SubProcess3.Parameters.OutputRecordCollection.Caption" Value="Output record collection" />
			<Item Name="BaseElements.SubProcess3.Parameters.OutputRecordCollection.MktgFunds.Caption" Value="MktgFunds" />
			<Item Name="BaseElements.SubProcess3.Parameters.OutputRecordCollection.MktgPlans.Caption" Value="MktgPlans" />
			<Item Name="BaseElements.SubProcess3.Parameters.OutputRecordCollection.Request.Caption" Value="Request" />
			<Item Name="BaseElements.SubProcess3.Parameters.OutputRecordCollection.transferamount.Caption" Value="transferamount" />
			<Item Name="BaseElements.SubProcess3.Parameters.TerminatedIterationsCount.Caption" Value="Number of terminated instances" />
			<Item Name="BaseElements.SubProcess3.Parameters.TotalIterationsCount.Caption" Value="Total number of instances" />
			<Item Name="Caption" Value="Approve Transfers" />
			<Item Name="LaneSets.LaneSet1.Caption" Value="LaneSet 1" />
			<Item Name="LaneSets.LaneSet1.Lanes.Lane1.Caption" Value="Lane 1" />
			<Item Name="NotificationCaption.Caption" Value="Process instance caption" />
			<Item Name="NotificationCaption.DisplayValue" Value="[#Process name#]" />
			<Item Name="Parameters.ProcessSchemaParameter2.Caption" Value="request id" />
		</Items>
	</Group>
</Resources>